passagemath_categories/__init__.py
passagemath_categories-10.6.47.dist-info/DELVEWHEEL
passagemath_categories-10.6.47.dist-info/METADATA
passagemath_categories-10.6.47.dist-info/RECORD
passagemath_categories-10.6.47.dist-info/top_level.txt
passagemath_categories-10.6.47.dist-info/WHEEL
passagemath_categories.libs/libgmp-10-6a8fe126122672a8aed2558e30454e74.dll
passagemath_categories.libs/msvcp140-a4c2229bdc2a2a630acdc095b4d86008.dll
sage/all__sagemath_categories.py
sage/arith/all.py
sage/arith/constants.pxd
sage/arith/functions.cp312-win_amd64.pyd
sage/arith/functions.pxd
sage/arith/functions.pyx
sage/arith/misc.py
sage/arith/multi_modular.cp312-win_amd64.pyd
sage/arith/multi_modular.pxd
sage/arith/multi_modular.pyx
sage/arith/rational_reconstruction.cp312-win_amd64.pyd
sage/arith/rational_reconstruction.pxd
sage/arith/rational_reconstruction.pyx
sage/arith/srange.cp312-win_amd64.pyd
sage/arith/srange.pyx
sage/calculus/all__sagemath_categories.py
sage/calculus/functional.py
sage/calculus/functions.py
sage/categories/additive_groups.py
sage/categories/additive_magmas.py
sage/categories/additive_monoids.py
sage/categories/additive_semigroups.py
sage/categories/affine_weyl_groups.py
sage/categories/algebras.py
sage/categories/algebras_with_basis.py
sage/categories/algebra_ideals.py
sage/categories/algebra_modules.py
sage/categories/all.py
sage/categories/aperiodic_semigroups.py
sage/categories/associative_algebras.py
sage/categories/bialgebras.py
sage/categories/bialgebras_with_basis.py
sage/categories/bimodules.py
sage/categories/chain_complexes.py
sage/categories/classical_crystals.py
sage/categories/coalgebras.py
sage/categories/coalgebras_with_basis.py
sage/categories/coercion_methods.cp312-win_amd64.pyd
sage/categories/coercion_methods.pyx
sage/categories/commutative_additive_groups.py
sage/categories/commutative_additive_monoids.py
sage/categories/commutative_additive_semigroups.py
sage/categories/commutative_algebras.py
sage/categories/commutative_algebra_ideals.py
sage/categories/commutative_rings.py
sage/categories/commutative_ring_ideals.py
sage/categories/complete_discrete_valuation.py
sage/categories/complex_reflection_groups.py
sage/categories/complex_reflection_or_generalized_coxeter_groups.py
